overturetoosm/__about__.py
overturetoosm/__init__.py
overturetoosm/__main__.py
overturetoosm/addresses.py
overturetoosm/buildings.py
overturetoosm/cli.py
overturetoosm/objects.py
overturetoosm/places.py
overturetoosm/resources.py
overturetoosm/segments.py
overturetoosm/utils.py
overturetoosm-1.1.0.dist-info/METADATA
overturetoosm-1.1.0.dist-info/WHEEL
overturetoosm-1.1.0.dist-info/licenses/LICENSE.txt
overturetoosm-1.1.0.dist-info/RECORD
