Metadata-Version: 2.3
Name: overturetoosm
Version: 1.1.0
Summary: Translate the Overture maps schema to OpenStreetMap tags.
Project-URL: Documentation, https://whubsch.github.io/overturetoosm/index.html
Project-URL: Issues, https://github.com/whubsch/overturetoosm/issues
Project-URL: Source, https://github.com/whubsch/overturetoosm
Author-email: Will <wahubsch@gmail.com>
License-Expression: MIT
License-File: LICENSE.txt
Keywords: mapping,openstreetmap,osm,overture,overture maps
Classifier: Development Status :: 4 - Beta
Classifier: License :: OSI Approved :: MIT License
Classifier: Programming Language :: Python
Classifier: Programming Language :: Python :: 3 :: Only
Classifier: Programming Language :: Python :: 3.10
Classifier: Programming Language :: Python :: 3.11
Classifier: Programming Language :: Python :: 3.12
Classifier: Programming Language :: Python :: 3.13
Classifier: Programming Language :: Python :: Implementation :: CPython
Classifier: Programming Language :: Python :: Implementation :: PyPy
Classifier: Typing :: Typed
Requires-Python: >=3.10
Requires-Dist: pydantic>=2.11.7
